{
  "elements": [
    {
      "title": "Concurs d'Instagram",
      "points": 100,
      "winner": "Trons"
    },
    {
      "title": "Prova escoles",
      "points": 100,
      "winner": "Llamps"
    },
    {
      "title": "Biblioteca Els Safreigs",
      "points": 100,
      "winner": "Trons"
    },
    {
      "title": "Gimcana d'El Tallaret",
      "points": 200,
      "winner": "no"
    },
    {
      "title": "Torneig de Botifarra",
      "points": 100,
      "winner": "no"
    },
    {
      "title": "Prova Sorpresa",
      "points": 100,
      "winner": "Llamps"
    },
    {
      "title": "Pescapunts i Punteria",
      "points": 100,
      "winner": "no"
    },
    {
      "title": "Correbars",
      "points": 100,
      "winner": "Trons"
    },
    {
      "title": "Bàsquet Nocturn",
      "points": 100,
      "winner": "Anul·lat"
    },
    {
      "title": "Torneig de Futbet",
      "points": 100,
      "winner": "no"
    },
    {
      "title": "Torneig de Petanca",
      "points": 100,
      "winner": "no"
    },
    {
      "title": "Torneig de Tenis Taula",
      "points": 100,
      "winner": "no"
    },
    {
      "title": "Llançament de pinyols d'oliva infantil",
      "points": 100,
      "winner": "Llamps"
    },
   {
      "title": "Llançament de pinyols d'oliva adult",
      "points": 100,
      "winner": "Trons"
    },
    {
      "title": "Torneig d'Escacs",
      "points": 100,
      "winner": "no"
    },
    {
      "title": "Tarda d'Esplais",
      "points": 300,
      "winner": "no"
    },
    {
      "title": "Torneig d'Hanbol",
      "points": 100,
      "winner": "no"
    },
    {
      "title": "Joc del Rotllo",
      "points": 100,
      "winner": "no"
    },
    {
      "title": "Cursa de carretons",
      "points": 100,
      "winner": "no"
    },
    {
      "title": "Prova Bantuany",
      "points": 100,
      "winner": "Llamps"
    }
  ]
}
